pytest_httpchain_jsonref/__init__.py
pytest_httpchain_jsonref/exceptions.py
pytest_httpchain_jsonref/loader.py
pytest_httpchain_jsonref/plumbing/__init__.py
pytest_httpchain_jsonref/plumbing/circular.py
pytest_httpchain_jsonref/plumbing/path.py
pytest_httpchain_jsonref/plumbing/reference.py
pytest_httpchain_jsonref-0.2.1.dist-info/WHEEL
pytest_httpchain_jsonref-0.2.1.dist-info/METADATA
pytest_httpchain_jsonref-0.2.1.dist-info/RECORD
