Metadata-Version: 2.3
Name: pytest-httpchain-jsonref
Version: 0.2.1
Summary: JSON reference ($ref) support for pytest-httpchain
Author: Alexander Eresov
Author-email: Alexander Eresov <aeresov@gmail.com>
Requires-Dist: deepmerge>=2.0
Requires-Python: >=3.13
